README.rst
setup.py
correos_chile/connector.py
correos_chile/handler.py
correos_chile/settings.py
django_correos_chile_rest.egg-info/PKG-INFO
django_correos_chile_rest.egg-info/SOURCES.txt
django_correos_chile_rest.egg-info/dependency_links.txt
django_correos_chile_rest.egg-info/top_level.txt