Metadata-Version: 2.1
Name: django-correos-chile-rest
Version: 1.0.1
Summary: Django Correos Chile Integration
Home-page: https://gitlab.com/linets/ecommerce/oms/integrations/django-correos-chile/
Author: Linets Development Team
Author-email: dteam@linets.cl
License: MIT
Platform: UNKNOWN
Requires-Python: >=3.7
